odoo/addons/maintenance_equipment_image/README.rst
odoo/addons/maintenance_equipment_image/__init__.py
odoo/addons/maintenance_equipment_image/__manifest__.py
odoo/addons/maintenance_equipment_image/i18n/es.po
odoo/addons/maintenance_equipment_image/i18n/it.po
odoo/addons/maintenance_equipment_image/i18n/maintenance_equipment_image.pot
odoo/addons/maintenance_equipment_image/models/__init__.py
odoo/addons/maintenance_equipment_image/models/maintenance_equipment.py
odoo/addons/maintenance_equipment_image/readme/CONTRIBUTORS.rst
odoo/addons/maintenance_equipment_image/readme/DESCRIPTION.rst
odoo/addons/maintenance_equipment_image/static/description/icon.png
odoo/addons/maintenance_equipment_image/static/description/index.html
odoo/addons/maintenance_equipment_image/tests/__init__.py
odoo/addons/maintenance_equipment_image/tests/test_maintenance_equipment_image.py
odoo/addons/maintenance_equipment_image/views/maintenance_equipment_views.xml
odoo12_addon_maintenance_equipment_image-12.0.1.0.0.99.dev8.dist-info/METADATA
odoo12_addon_maintenance_equipment_image-12.0.1.0.0.99.dev8.dist-info/WHEEL
odoo12_addon_maintenance_equipment_image-12.0.1.0.0.99.dev8.dist-info/top_level.txt
odoo12_addon_maintenance_equipment_image-12.0.1.0.0.99.dev8.dist-info/RECORD
